sadisplay/__init__.py
sadisplay/describe.py
sadisplay/reflect.py
sadisplay/render.py
sadisplay-0.4.9.dist-info/DESCRIPTION.rst
sadisplay-0.4.9.dist-info/METADATA
sadisplay-0.4.9.dist-info/RECORD
sadisplay-0.4.9.dist-info/WHEEL
sadisplay-0.4.9.dist-info/entry_points.txt
sadisplay-0.4.9.dist-info/metadata.json
sadisplay-0.4.9.dist-info/top_level.txt
