Metadata-Version: 2.0
Name: sadisplay
Version: 0.4.9
Summary: SqlAlchemy schema display script
Home-page: http://bitbucket.org/estin/sadisplay
Author: Evgeniy Tatarkin
Author-email: tatarkin.evg@gmail.com
License: BSD
Platform: any
Classifier: Intended Audience :: Developers
Classifier: License :: OSI Approved :: BSD License
Classifier: Operating System :: OS Independent
Classifier: Programming Language :: Python
Classifier: Programming Language :: Python :: 3
Requires-Dist: SQLAlchemy (>=0.5)
